{
  "ticker": "JPM",
  "key": "JPM_Q2_2025",
  "year": 2025,
  "quarter": 2,
  "verified_at": "2026-02-13T12:10:17.502800",
  "claims_with_verdicts": [
    {
      "claim": {
        "speaker_role": "cfo",
        "claim_type": "absolute",
        "speaker": "Jeremy Barnum",
        "qualifiers": [],
        "quote_text": "this quarter, the firm reported net income of $15 billion",
        "claimed_value_raw": "$15 billion",
        "claimed_value": 15,
        "gaap_classification": "gaap",
        "period": "Q2 2025",
        "quote_start_char": null,
        "confidence": 1,
        "scale": "billions",
        "quote_end_char": null,
        "metric_context": "Total",
        "unit": "dollars",
        "metric_type": "net_income",
        "is_approximate": false,
        "claim_id": "claim_001"
      },
      "verification": {
        "claim_id": "claim_001",
        "claimed_value": 15,
        "actual_value": 14987000000,
        "difference": 13000000,
        "difference_pct": 0.0867418429305398,
        "tolerance_used": 0.01,
        "computation_detail": "Claimed 15,000,000,000.00 vs Actual 14,987,000,000.00. Diff: 0.09% (threshold: 1.0%)",
        "computation_steps": [
          {
            "step": "Absolute comparison",
            "formula": "|15,000,000,000.00 - 14,987,000,000.00| / |14,987,000,000.00|",
            "result": 0.000867418429305398,
            "threshold": 0.01
          }
        ],
        "financial_facts_used": [
          {
            "field": "net_income",
            "fy": 2025,
            "fq": 2,
            "value": 14987000000
          }
        ],
        "evidence_source": "fmp",
        "flags": [],
        "misleading_flags": [],
        "misleading_reasons": [],
        "explanation": "Verified: claimed 15,000,000,000.00 vs actual 14,987,000,000.00 from fmp.",
        "verdict": "verified"
      }
    },
    {
      "claim": {
        "is_approximate": false,
        "claim_id": "claim_002",
        "metric_type": "eps_diluted",
        "unit": "per_share",
        "metric_context": "Total",
        "quote_end_char": 135,
        "scale": null,
        "confidence": 1,
        "quote_start_char": 123,
        "period": "Q2 2025",
        "claimed_value": 5.24,
        "gaap_classification": "gaap",
        "quote_text": "EPS of $5.24",
        "claimed_value_raw": "$5.24",
        "qualifiers": [],
        "speaker": "Jeremy Barnum",
        "claim_type": "absolute",
        "speaker_role": "cfo"
      },
      "verification": {
        "claim_id": "claim_002",
        "claimed_value": 5.24,
        "actual_value": 5.24,
        "difference": 0.0,
        "difference_pct": 0.0,
        "tolerance_used": 0.015,
        "computation_detail": "EPS: claimed $5.24 vs actual $5.24. Diff $0.000 within $0.015 tolerance.",
        "computation_steps": [
          {
            "step": "EPS absolute comparison",
            "formula": "|5.24 - 5.24| = 0.000",
            "result": 0.0,
            "threshold": 0.015
          }
        ],
        "financial_facts_used": [
          {
            "field": "eps_diluted",
            "fy": 2025,
            "fq": 2,
            "value": 5.24
          }
        ],
        "evidence_source": "fmp",
        "flags": [],
        "misleading_flags": [],
        "misleading_reasons": [],
        "explanation": "Verified: claimed $5.24 matches actual $5.24.",
        "verdict": "verified"
      }
    },
    {
      "claim": {
        "claim_type": "absolute",
        "speaker_role": "cfo",
        "speaker": "Jeremy Barnum",
        "qualifiers": [],
        "period": "Q2 2025",
        "gaap_classification": "gaap",
        "claimed_value": 45.7,
        "claimed_value_raw": "$45.7 billion",
        "quote_text": "revenue of $45.7 billion",
        "quote_start_char": 139,
        "scale": "billions",
        "confidence": 1,
        "claim_id": "claim_003",
        "is_approximate": false,
        "metric_type": "revenue",
        "unit": "dollars",
        "metric_context": "Total",
        "quote_end_char": 163
      },
      "verification": {
        "claim_id": "claim_003",
        "claimed_value": 45.7,
        "actual_value": null,
        "difference": null,
        "difference_pct": null,
        "tolerance_used": null,
        "computation_detail": null,
        "computation_steps": [],
        "financial_facts_used": [],
        "evidence_source": null,
        "flags": [
          "revenue_definition_mismatch"
        ],
        "misleading_flags": [],
        "misleading_reasons": [],
        "explanation": "Claimed revenue ($45.7B) is 65% of data source revenue ($69.9B). This likely reflects a difference in revenue definition (e.g., net revenue vs gross revenue for financial institutions).",
        "verdict": "unverifiable"
      }
    },
    {
      "claim": {
        "metric_context": "Total",
        "quote_end_char": 185,
        "unit": "percent",
        "metric_type": "other",
        "claim_id": "claim_004",
        "is_approximate": false,
        "confidence": 1,
        "scale": null,
        "quote_start_char": 165,
        "quote_text": "with an ROTCE of 21%",
        "claimed_value_raw": "21%",
        "claimed_value": 21,
        "gaap_classification": "gaap",
        "period": "Q2 2025",
        "qualifiers": [],
        "speaker": "Jeremy Barnum",
        "speaker_role": "cfo",
        "claim_type": "absolute"
      },
      "verification": {
        "claim_id": "claim_004",
        "claimed_value": 21,
        "actual_value": null,
        "difference": null,
        "difference_pct": null,
        "tolerance_used": null,
        "computation_detail": null,
        "computation_steps": [],
        "financial_facts_used": [],
        "evidence_source": null,
        "flags": [],
        "misleading_flags": [],
        "misleading_reasons": [],
        "explanation": "Metric 'other' not in verification catalog.",
        "verdict": "unverifiable"
      }
    },
    {
      "claim": {
        "qualifiers": [],
        "speaker": "Jeremy Barnum",
        "claim_type": "yoy_growth",
        "speaker_role": "cfo",
        "claim_id": "claim_005",
        "is_approximate": false,
        "metric_type": "revenue",
        "unit": "percent",
        "metric_context": "Total",
        "quote_end_char": 440,
        "scale": null,
        "confidence": 1,
        "quote_start_char": 376,
        "period": "Q2 2025",
        "gaap_classification": "gaap",
        "claimed_value": 10,
        "claimed_value_raw": "10%",
        "quote_text": "revenue of $45.7 billion, down $5.3 billion, or 10% year-on-year",
        "comparison_period": "Q2 2024"
      },
      "verification": {
        "claim_id": "claim_005",
        "claimed_value": 10,
        "actual_value": null,
        "difference": null,
        "difference_pct": null,
        "tolerance_used": null,
        "computation_detail": null,
        "computation_steps": [],
        "financial_facts_used": [],
        "evidence_source": null,
        "flags": [],
        "misleading_flags": [],
        "misleading_reasons": [],
        "explanation": "Missing data for period(s): Q2 2024",
        "verdict": "unverifiable"
      }
    },
    {
      "claim": {
        "quote_start_char": 442,
        "claimed_value": 1,
        "gaap_classification": "non_gaap",
        "period": "Q2 2025",
        "comparison_period": "Q2 2024",
        "claimed_value_raw": "1%",
        "quote_text": "NII ex Markets was down $185 million, or 1%",
        "metric_type": "other",
        "claim_id": "claim_006",
        "is_approximate": false,
        "quote_end_char": 485,
        "metric_context": "NII ex Markets",
        "unit": "percent",
        "scale": null,
        "confidence": 1,
        "speaker": "Jeremy Barnum",
        "claim_type": "yoy_growth",
        "speaker_role": "cfo",
        "qualifiers": []
      },
      "verification": {
        "claim_id": "claim_006",
        "claimed_value": 1,
        "actual_value": null,
        "difference": null,
        "difference_pct": null,
        "tolerance_used": null,
        "computation_detail": null,
        "computation_steps": [],
        "financial_facts_used": [],
        "evidence_source": null,
        "flags": [
          "non_gaap_claim"
        ],
        "misleading_flags": [],
        "misleading_reasons": [],
        "explanation": "This claim references a non-GAAP metric. Our data sources contain GAAP figures only. Non-GAAP metrics exclude items like stock-based compensation or restructuring charges.",
        "verdict": "unverifiable"
      }
    },
    {
      "claim": {
        "comparison_period": "Q2 2024",
        "quote_text": "NIR ex Markets was down $6.3 billion, or 31%",
        "claimed_value_raw": "31%",
        "claimed_value": 31,
        "gaap_classification": "non_gaap",
        "period": "Q2 2025",
        "quote_start_char": 719,
        "confidence": 1,
        "scale": null,
        "quote_end_char": 763,
        "metric_context": "NIR ex Markets",
        "unit": "percent",
        "metric_type": "other",
        "claim_id": "claim_007",
        "is_approximate": false,
        "speaker_role": "cfo",
        "claim_type": "yoy_growth",
        "speaker": "Jeremy Barnum",
        "qualifiers": []
      },
      "verification": {
        "claim_id": "claim_007",
        "claimed_value": 31,
        "actual_value": null,
        "difference": null,
        "difference_pct": null,
        "tolerance_used": null,
        "computation_detail": null,
        "computation_steps": [],
        "financial_facts_used": [],
        "evidence_source": null,
        "flags": [
          "non_gaap_claim"
        ],
        "misleading_flags": [],
        "misleading_reasons": [],
        "explanation": "This claim references a non-GAAP metric. Our data sources contain GAAP figures only. Non-GAAP metrics exclude items like stock-based compensation or restructuring charges.",
        "verdict": "unverifiable"
      }
    },
    {
      "claim": {
        "speaker": "Jeremy Barnum",
        "claim_type": "yoy_growth",
        "speaker_role": "cfo",
        "qualifiers": [],
        "quote_start_char": 874,
        "period": "Q2 2025",
        "claimed_value": 8,
        "gaap_classification": "non_gaap",
        "claimed_value_raw": "8%",
        "quote_text": "up $1 billion, or 8%",
        "comparison_period": "Q2 2024",
        "is_approximate": false,
        "claim_id": "claim_008",
        "metric_type": "other",
        "unit": "percent",
        "metric_context": "NIR ex Markets excluding Visa/securities losses",
        "quote_end_char": 894,
        "scale": null,
        "confidence": 1
      },
      "verification": {
        "claim_id": "claim_008",
        "claimed_value": 8,
        "actual_value": null,
        "difference": null,
        "difference_pct": null,
        "tolerance_used": null,
        "computation_detail": null,
        "computation_steps": [],
        "financial_facts_used": [],
        "evidence_source": null,
        "flags": [
          "non_gaap_claim"
        ],
        "misleading_flags": [],
        "misleading_reasons": [],
        "explanation": "This claim references a non-GAAP metric. Our data sources contain GAAP figures only. Non-GAAP metrics exclude items like stock-based compensation or restructuring charges.",
        "verdict": "unverifiable"
      }
    },
    {
      "claim": {
        "qualifiers": [],
        "speaker": "Jeremy Barnum",
        "speaker_role": "cfo",
        "claim_type": "yoy_growth",
        "unit": "percent",
        "metric_context": "Markets",
        "quote_end_char": 1065,
        "claim_id": "claim_009",
        "is_approximate": false,
        "metric_type": "revenue",
        "confidence": 1,
        "scale": null,
        "quote_start_char": 1023,
        "quote_text": "Markets revenue was up $1.1 billion or 15%",
        "claimed_value_raw": "15%",
        "comparison_period": "Q2 2024",
        "period": "Q2 2025",
        "claimed_value": 15,
        "gaap_classification": "gaap"
      },
      "verification": {
        "claim_id": "claim_009",
        "claimed_value": 15,
        "actual_value": null,
        "difference": null,
        "difference_pct": null,
        "tolerance_used": null,
        "computation_detail": null,
        "computation_steps": [],
        "financial_facts_used": [],
        "evidence_source": null,
        "flags": [
          "segment_claim"
        ],
        "misleading_flags": [],
        "misleading_reasons": [],
        "explanation": "This is a Markets revenue growth claim. Our data only includes total company-level figures.",
        "verdict": "unverifiable"
      }
    },
    {
      "claim": {
        "scale": null,
        "confidence": 1,
        "metric_type": "operating_expenses",
        "claim_id": "claim_010",
        "is_approximate": false,
        "metric_context": "Expenses excluding Visa contribution",
        "quote_end_char": null,
        "unit": "percent",
        "gaap_classification": "non_gaap",
        "claimed_value": 5,
        "period": "Q2 2025",
        "comparison_period": "Q2 2024",
        "claimed_value_raw": "5%",
        "quote_text": "excluding last year's Visa stock contribution... was up $1.1 billion, or 5%",
        "quote_start_char": null,
        "qualifiers": [],
        "claim_type": "yoy_growth",
        "speaker_role": "cfo",
        "speaker": "Jeremy Barnum"
      },
      "verification": {
        "claim_id": "claim_010",
        "claimed_value": 5,
        "actual_value": null,
        "difference": null,
        "difference_pct": null,
        "tolerance_used": null,
        "computation_detail": null,
        "computation_steps": [],
        "financial_facts_used": [],
        "evidence_source": null,
        "flags": [
          "non_gaap_claim"
        ],
        "misleading_flags": [],
        "misleading_reasons": [],
        "explanation": "This claim references a non-GAAP metric. Our data sources contain GAAP figures only. Non-GAAP metrics exclude items like stock-based compensation or restructuring charges.",
        "verdict": "unverifiable"
      }
    },
    {
      "claim": {
        "qualifiers": [],
        "claim_type": "absolute",
        "speaker_role": "cfo",
        "speaker": "Jeremy Barnum",
        "scale": "billions",
        "confidence": 1,
        "is_approximate": false,
        "claim_id": "claim_011",
        "metric_type": "other",
        "unit": "dollars",
        "quote_end_char": 1368,
        "metric_context": "Total",
        "period": "Q2 2025",
        "claimed_value": 2.8,
        "gaap_classification": "gaap",
        "claimed_value_raw": "$2.8 billion",
        "quote_text": "credit costs were $2.8 billion",
        "quote_start_char": 1338
      },
      "verification": {
        "claim_id": "claim_011",
        "claimed_value": 2.8,
        "actual_value": null,
        "difference": null,
        "difference_pct": null,
        "tolerance_used": null,
        "computation_detail": null,
        "computation_steps": [],
        "financial_facts_used": [],
        "evidence_source": null,
        "flags": [],
        "misleading_flags": [],
        "misleading_reasons": [],
        "explanation": "Metric 'other' not in verification catalog.",
        "verdict": "unverifiable"
      }
    },
    {
      "claim": {
        "gaap_classification": "gaap",
        "claimed_value": 15,
        "period": "Q2 2025",
        "claimed_value_raw": "15%",
        "quote_text": "We ended the quarter with a CET1 ratio of 15%",
        "quote_start_char": 1652,
        "scale": null,
        "confidence": 1,
        "metric_type": "other",
        "claim_id": "claim_012",
        "is_approximate": false,
        "metric_context": "CET1 Ratio",
        "quote_end_char": 1697,
        "unit": "percent",
        "claim_type": "absolute",
        "speaker_role": "cfo",
        "speaker": "Jeremy Barnum",
        "qualifiers": []
      },
      "verification": {
        "claim_id": "claim_012",
        "claimed_value": 15,
        "actual_value": null,
        "difference": null,
        "difference_pct": null,
        "tolerance_used": null,
        "computation_detail": null,
        "computation_steps": [],
        "financial_facts_used": [],
        "evidence_source": null,
        "flags": [],
        "misleading_flags": [],
        "misleading_reasons": [],
        "explanation": "Metric 'other' not in verification catalog.",
        "verdict": "unverifiable"
      }
    },
    {
      "claim": {
        "claim_type": "qoq_growth",
        "speaker_role": "cfo",
        "speaker": "Jeremy Barnum",
        "qualifiers": [],
        "period": "Q2 2025",
        "claimed_value": 40,
        "gaap_classification": "gaap",
        "quote_text": "down 40 basis points versus the prior quarter",
        "claimed_value_raw": "40 basis points",
        "comparison_period": "Q1 2025",
        "quote_start_char": 1699,
        "scale": null,
        "confidence": 1,
        "claim_id": "claim_013",
        "is_approximate": false,
        "metric_type": "other",
        "unit": "basis_points",
        "metric_context": "CET1 Ratio",
        "quote_end_char": 1744
      },
      "verification": {
        "claim_id": "claim_013",
        "claimed_value": 40,
        "actual_value": null,
        "difference": null,
        "difference_pct": null,
        "tolerance_used": null,
        "computation_detail": null,
        "computation_steps": [],
        "financial_facts_used": [],
        "evidence_source": null,
        "flags": [],
        "misleading_flags": [],
        "misleading_reasons": [],
        "explanation": "Metric 'other' not in verification catalog.",
        "verdict": "unverifiable"
      }
    },
    {
      "claim": {
        "speaker_role": "cfo",
        "claim_type": "absolute",
        "speaker": "Jeremy Barnum",
        "qualifiers": [
          "intention"
        ],
        "quote_text": "Board's intention to increase the dividend to $1.50 per share",
        "claimed_value_raw": "$1.50 per share",
        "claimed_value": 1.5,
        "gaap_classification": "gaap",
        "period": "Q3 2025",
        "quote_start_char": 2196,
        "confidence": 1,
        "scale": null,
        "quote_end_char": 2257,
        "metric_context": "Dividend",
        "unit": "per_share",
        "metric_type": "other",
        "claim_id": "claim_014",
        "is_approximate": false
      },
      "verification": {
        "claim_id": "claim_014",
        "claimed_value": 1.5,
        "actual_value": null,
        "difference": null,
        "difference_pct": null,
        "tolerance_used": null,
        "computation_detail": null,
        "computation_steps": [],
        "financial_facts_used": [],
        "evidence_source": null,
        "flags": [],
        "misleading_flags": [],
        "misleading_reasons": [],
        "explanation": "Metric 'other' not in verification catalog.",
        "verdict": "unverifiable"
      }
    },
    {
      "claim": {
        "is_approximate": false,
        "claim_id": "claim_015",
        "metric_type": "revenue",
        "unit": "percent",
        "metric_context": "CCB",
        "quote_end_char": 2428,
        "scale": null,
        "confidence": 1,
        "quote_start_char": 2331,
        "period": "Q2 2025",
        "gaap_classification": "gaap",
        "claimed_value": 6,
        "claimed_value_raw": "6%",
        "quote_text": "CCB reported net income of $5.2 billion on revenue of $18.8 billion, which was up 6% year-on-year",
        "comparison_period": "Q2 2024",
        "qualifiers": [],
        "speaker": "Jeremy Barnum",
        "claim_type": "yoy_growth",
        "speaker_role": "cfo"
      },
      "verification": {
        "claim_id": "claim_015",
        "claimed_value": 6,
        "actual_value": null,
        "difference": null,
        "difference_pct": null,
        "tolerance_used": null,
        "computation_detail": null,
        "computation_steps": [],
        "financial_facts_used": [],
        "evidence_source": null,
        "flags": [
          "segment_claim"
        ],
        "misleading_flags": [],
        "misleading_reasons": [],
        "explanation": "This is a CCB revenue growth claim. Our data only includes total company-level figures.",
        "verdict": "unverifiable"
      }
    },
    {
      "claim": {
        "claimed_value": 14,
        "gaap_classification": "gaap",
        "period": "Q2 2025",
        "comparison_period": "Q2 2024",
        "claimed_value_raw": "14%",
        "quote_text": "Client investment assets were up 14% year-on-year",
        "quote_start_char": 2635,
        "scale": null,
        "confidence": 1,
        "metric_type": "other",
        "is_approximate": false,
        "claim_id": "claim_016",
        "metric_context": "CCB Client investment assets",
        "quote_end_char": 2684,
        "unit": "percent",
        "claim_type": "yoy_growth",
        "speaker_role": "cfo",
        "speaker": "Jeremy Barnum",
        "qualifiers": []
      },
      "verification": {
        "claim_id": "claim_016",
        "claimed_value": 14,
        "actual_value": null,
        "difference": null,
        "difference_pct": null,
        "tolerance_used": null,
        "computation_detail": null,
        "computation_steps": [],
        "financial_facts_used": [],
        "evidence_source": null,
        "flags": [],
        "misleading_flags": [],
        "misleading_reasons": [],
        "explanation": "Metric 'other' not in verification catalog.",
        "verdict": "unverifiable"
      }
    },
    {
      "claim": {
        "quote_start_char": 2862,
        "claimed_value_raw": "15%",
        "quote_text": "Card Services & Auto, revenue was up 15% year-on-year",
        "comparison_period": "Q2 2024",
        "period": "Q2 2025",
        "claimed_value": 15,
        "gaap_classification": "gaap",
        "unit": "percent",
        "metric_context": "Card Services & Auto revenue",
        "quote_end_char": 2915,
        "is_approximate": false,
        "claim_id": "claim_017,claim_type:",
        "metric_type": "revenue",
        "confidence": 1,
        "scale": null,
        "speaker": "Jeremy Barnum",
        "speaker_role": "cfo",
        "claim_type": "yoy_growth",
        "qualifiers": []
      },
      "verification": {
        "claim_id": "claim_017,claim_type:",
        "claimed_value": 15,
        "actual_value": null,
        "difference": null,
        "difference_pct": null,
        "tolerance_used": null,
        "computation_detail": null,
        "computation_steps": [],
        "financial_facts_used": [],
        "evidence_source": null,
        "flags": [
          "segment_claim"
        ],
        "misleading_flags": [],
        "misleading_reasons": [],
        "explanation": "This is a Card Services & Auto revenue revenue growth claim. Our data only includes total company-level figures.",
        "verdict": "unverifiable"
      }
    },
    {
      "claim": {
        "speaker": "Jeremy Barnum",
        "speaker_role": "cfo",
        "claim_type": "yoy_growth",
        "qualifiers": [],
        "quote_start_char": 3030,
        "quote_text": "Card outstandings were up 9% due to strong new card acquisition",
        "claimed_value_raw": "9%",
        "comparison_period": "Q2 2024",
        "period": "Q2 2025",
        "claimed_value": 9,
        "gaap_classification": "gaap",
        "unit": "percent",
        "quote_end_char": 3093,
        "metric_context": "Card outstandings",
        "claim_id": "claim_018",
        "is_approximate": false,
        "metric_type": "other",
        "confidence": 1,
        "scale": null
      },
      "verification": {
        "claim_id": "claim_018",
        "claimed_value": 9,
        "actual_value": null,
        "difference": null,
        "difference_pct": null,
        "tolerance_used": null,
        "computation_detail": null,
        "computation_steps": [],
        "financial_facts_used": [],
        "evidence_source": null,
        "flags": [],
        "misleading_flags": [],
        "misleading_reasons": [],
        "explanation": "Metric 'other' not in verification catalog.",
        "verdict": "unverifiable"
      }
    },
    {
      "claim": {
        "gaap_classification": "gaap",
        "claimed_value": 9,
        "period": "Q2 2025",
        "comparison_period": "Q2 2024",
        "claimed_value_raw": "9%",
        "quote_text": "CIB reported net income of $6.7 billion, on revenue of $19.5 billion, which was up 9% year-on-year",
        "quote_start_char": 3451,
        "scale": null,
        "confidence": 1,
        "metric_type": "revenue",
        "is_approximate": false,
        "claim_id": "claim_019",
        "metric_context": "CIB revenue",
        "quote_end_char": 3549,
        "unit": "percent",
        "claim_type": "yoy_growth",
        "speaker_role": "cfo",
        "speaker": "Jeremy Barnum",
        "qualifiers": []
      },
      "verification": {
        "claim_id": "claim_019",
        "claimed_value": 9,
        "actual_value": null,
        "difference": null,
        "difference_pct": null,
        "tolerance_used": null,
        "computation_detail": null,
        "computation_steps": [],
        "financial_facts_used": [],
        "evidence_source": null,
        "flags": [
          "segment_claim"
        ],
        "misleading_flags": [],
        "misleading_reasons": [],
        "explanation": "This is a CIB revenue revenue growth claim. Our data only includes total company-level figures.",
        "verdict": "unverifiable"
      }
    },
    {
      "claim": {
        "qualifiers": [
          "rank #1"
        ],
        "claim_type": "absolute",
        "speaker_role": "cfo",
        "speaker": "Jeremy Barnum",
        "scale": null,
        "confidence": 1,
        "is_approximate": false,
        "claim_id": "claim_020",
        "metric_type": "other",
        "unit": "percent",
        "quote_end_char": 3632,
        "metric_context": "CIB wallet share",
        "period": "Q2 2025,qualifiers:[",
        "claimed_value": 8.9,
        "gaap_classification": "gaap",
        "claimed_value_raw": "8.9%",
        "quote_text": "rank #1 with wallet share of 8.9%",
        "quote_start_char": 3599
      },
      "verification": {
        "claim_id": "claim_020",
        "claimed_value": 8.9,
        "actual_value": null,
        "difference": null,
        "difference_pct": null,
        "tolerance_used": null,
        "computation_detail": null,
        "computation_steps": [],
        "financial_facts_used": [],
        "evidence_source": null,
        "flags": [],
        "misleading_flags": [],
        "misleading_reasons": [],
        "explanation": "Metric 'other' not in verification catalog.",
        "verdict": "unverifiable"
      }
    },
    {
      "claim": {
        "speaker": "Jeremy Barnum",
        "speaker_role": "cfo",
        "claim_type": "yoy_growth",
        "qualifiers": [],
        "quote_start_char": 4198,
        "claimed_value_raw": "15%",
        "quote_text": "Moving to Markets. Total revenue was up 15% year-on-year",
        "comparison_period": "Q2 2024",
        "period": "Q2 2025",
        "claimed_value": 15,
        "gaap_classification": "gaap",
        "unit": "percent",
        "metric_context": "Markets Total revenue",
        "quote_end_char": 4254,
        "is_approximate": false,
        "claim_id": "claim_021",
        "metric_type": "revenue",
        "confidence": 1,
        "scale": null
      },
      "verification": {
        "claim_id": "claim_021",
        "claimed_value": 15,
        "actual_value": null,
        "difference": null,
        "difference_pct": null,
        "tolerance_used": null,
        "computation_detail": null,
        "computation_steps": [],
        "financial_facts_used": [],
        "evidence_source": null,
        "flags": [
          "segment_claim"
        ],
        "misleading_flags": [],
        "misleading_reasons": [],
        "explanation": "This is a Markets Total revenue revenue growth claim. Our data only includes total company-level figures.",
        "verdict": "unverifiable"
      }
    },
    {
      "claim": {
        "quote_start_char": 5434,
        "gaap_classification": "gaap",
        "claimed_value": 34,
        "period": "Q2 2025",
        "claimed_value_raw": "34%",
        "quote_text": "AWM reported net income of $1.5 billion with a pretax margin of 34%",
        "metric_type": "operating_margin",
        "claim_id": "claim_022",
        "is_approximate": false,
        "metric_context": "AWM pretax margin",
        "quote_end_char": 5501,
        "unit": "percent",
        "scale": null,
        "confidence": 1,
        "speaker": "Jeremy Barnum",
        "claim_type": "absolute",
        "speaker_role": "cfo",
        "qualifiers": []
      },
      "verification": {
        "claim_id": "claim_022",
        "claimed_value": 34,
        "actual_value": null,
        "difference": null,
        "difference_pct": null,
        "tolerance_used": null,
        "computation_detail": null,
        "computation_steps": [],
        "financial_facts_used": [],
        "evidence_source": null,
        "flags": [],
        "misleading_flags": [],
        "misleading_reasons": [],
        "explanation": "No operating_margin data found for JPM Q2 2025.",
        "verdict": "unverifiable"
      }
    },
    {
      "claim": {
        "speaker": "Jeremy Barnum",
        "claim_type": "yoy_growth",
        "speaker_role": "cfo",
        "qualifiers": [],
        "quote_start_char": 6062,
        "period": "Q2 2025",
        "gaap_classification": "gaap",
        "claimed_value": 18,
        "claimed_value_raw": "18%",
        "quote_text": "AUM of $4.3 trillion was up 18% year-on-year",
        "comparison_period": "Q2 2024",
        "is_approximate": false,
        "claim_id": "claim_023",
        "metric_type": "other",
        "unit": "percent",
        "metric_context": "AUM",
        "quote_end_char": 6106,
        "scale": "trillions",
        "confidence": 1
      },
      "verification": {
        "claim_id": "claim_023",
        "claimed_value": 18,
        "actual_value": null,
        "difference": null,
        "difference_pct": null,
        "tolerance_used": null,
        "computation_detail": null,
        "computation_steps": [],
        "financial_facts_used": [],
        "evidence_source": null,
        "flags": [],
        "misleading_flags": [],
        "misleading_reasons": [],
        "explanation": "Metric 'other' not in verification catalog.",
        "verdict": "unverifiable"
      }
    },
    {
      "claim": {
        "quote_start_char": 7053,
        "claimed_value_raw": "$92 billion",
        "quote_text": "expect NII ex Markets to be approximately $92 billion",
        "gaap_classification": "non_gaap",
        "claimed_value": 92,
        "period": "FY 2025",
        "quote_end_char": 7106,
        "metric_context": "NII ex Markets",
        "unit": "dollars",
        "metric_type": "other",
        "is_approximate": true,
        "claim_id": "claim_024",
        "confidence": 1,
        "scale": "billions",
        "speaker": "Jeremy Barnum",
        "speaker_role": "cfo",
        "claim_type": "guidance",
        "qualifiers": [
          "approximately"
        ]
      },
      "verification": {
        "claim_id": "claim_024",
        "claimed_value": 92,
        "actual_value": null,
        "difference": null,
        "difference_pct": null,
        "tolerance_used": null,
        "computation_detail": null,
        "computation_steps": [],
        "financial_facts_used": [],
        "evidence_source": null,
        "flags": [
          "non_gaap_claim"
        ],
        "misleading_flags": [],
        "misleading_reasons": [],
        "explanation": "This claim references a non-GAAP metric. Our data sources contain GAAP figures only. Non-GAAP metrics exclude items like stock-based compensation or restructuring charges.",
        "verdict": "unverifiable"
      }
    },
    {
      "claim": {
        "confidence": 1,
        "scale": "billions",
        "quote_end_char": 7303,
        "metric_context": "Total NII",
        "unit": "dollars",
        "metric_type": "other",
        "is_approximate": true,
        "claim_id": "claim_025",
        "claimed_value_raw": "$95.5 billion",
        "quote_text": "Total NII guidance is now about $95.5 billion",
        "gaap_classification": "gaap",
        "claimed_value": 95.5,
        "period": "FY 2025",
        "quote_start_char": 7258,
        "qualifiers": [
          "about"
        ],
        "speaker_role": "cfo",
        "claim_type": "guidance",
        "speaker": "Jeremy Barnum"
      },
      "verification": {
        "claim_id": "claim_025",
        "claimed_value": 95.5,
        "actual_value": null,
        "difference": null,
        "difference_pct": null,
        "tolerance_used": null,
        "computation_detail": null,
        "computation_steps": [],
        "financial_facts_used": [],
        "evidence_source": null,
        "flags": [
          "guidance_claim"
        ],
        "misleading_flags": [],
        "misleading_reasons": [],
        "explanation": "Forward-looking guidance claims cannot be verified against historical data.",
        "verdict": "unverifiable"
      }
    },
    {
      "claim": {
        "qualifiers": [
          "about"
        ],
        "speaker_role": "cfo",
        "claim_type": "guidance",
        "speaker": "Jeremy Barnum",
        "confidence": 1,
        "scale": "billions",
        "unit": "dollars",
        "quote_end_char": 7414,
        "metric_context": "Adjusted expense",
        "is_approximate": true,
        "claim_id": "claim_026",
        "metric_type": "operating_expenses",
        "claimed_value_raw": "$95.5 billion",
        "quote_text": "on adjusted expense, we now expect it to be about $95.5 billion",
        "period": "FY 2025",
        "claimed_value": 95.5,
        "gaap_classification": "non_gaap",
        "quote_start_char": 7351
      },
      "verification": {
        "claim_id": "claim_026",
        "claimed_value": 95.5,
        "actual_value": null,
        "difference": null,
        "difference_pct": null,
        "tolerance_used": null,
        "computation_detail": null,
        "computation_steps": [],
        "financial_facts_used": [],
        "evidence_source": null,
        "flags": [
          "non_gaap_claim"
        ],
        "misleading_flags": [],
        "misleading_reasons": [],
        "explanation": "This claim references a non-GAAP metric. Our data sources contain GAAP figures only. Non-GAAP metrics exclude items like stock-based compensation or restructuring charges.",
        "verdict": "unverifiable"
      }
    },
    {
      "claim": {
        "qualifiers": [
          "approximately"
        ],
        "claim_type": "guidance",
        "speaker_role": "cfo",
        "speaker": "Jeremy Barnum",
        "scale": null,
        "confidence": 1,
        "metric_type": "other",
        "claim_id": "claim_027",
        "is_approximate": true,
        "metric_context": "Card net charge-off rate",
        "quote_end_char": 7606,
        "unit": "percent",
        "gaap_classification": "gaap",
        "claimed_value": 3.6,
        "period": "FY 2025",
        "claimed_value_raw": "3.6%",
        "quote_text": "expect the Card net charge-off rate to be approximately 3.6%",
        "quote_start_char": 7546
      },
      "verification": {
        "claim_id": "claim_027",
        "claimed_value": 3.6,
        "actual_value": null,
        "difference": null,
        "difference_pct": null,
        "tolerance_used": null,
        "computation_detail": null,
        "computation_steps": [],
        "financial_facts_used": [],
        "evidence_source": null,
        "flags": [
          "guidance_claim"
        ],
        "misleading_flags": [],
        "misleading_reasons": [],
        "explanation": "Forward-looking guidance claims cannot be verified against historical data.",
        "verdict": "unverifiable"
      }
    }
  ],
  "summary": {
    "total": 27,
    "verified": 2,
    "close_match": 0,
    "mismatch": 0,
    "misleading": 0,
    "unverifiable": 25
  }
}