{
  "ticker": "TSLA",
  "key": "TSLA_Q4_2025",
  "year": 2025,
  "quarter": 4,
  "verified_at": "2026-02-13T17:39:35.593666",
  "claims_with_verdicts": [
    {
      "claim": {
        "gaap_classification": "non_gaap",
        "claim_type": "absolute",
        "quote_end_char": 8652,
        "is_approximate": false,
        "speaker": "Vaibhav Taneja",
        "claimed_value_raw": "15.4%",
        "metric_type": "gross_margin",
        "metric_context": "Automotive",
        "scale": null,
        "quote_start_char": 8572,
        "period": "Q3 2025",
        "claimed_value": 15.4,
        "claim_id": "claim_001",
        "unit": "percent",
        "speaker_role": "cfo",
        "confidence": 1,
        "quote_text": "automotive margins, excluding credits, improved sequentially from 15.4% to 17.9%"
      },
      "verification": {
        "claim_id": "claim_001",
        "claimed_value": 15.4,
        "actual_value": null,
        "difference": null,
        "difference_pct": null,
        "tolerance_used": null,
        "computation_detail": null,
        "computation_steps": [],
        "financial_facts_used": [],
        "evidence_source": null,
        "flags": [
          "non_gaap_claim"
        ],
        "misleading_flags": [],
        "misleading_reasons": [],
        "explanation": "This claim references a non-GAAP metric. Our data sources contain GAAP figures only. Non-GAAP metrics exclude items like stock-based compensation or restructuring charges.",
        "verdict": "unverifiable"
      }
    },
    {
      "claim": {
        "unit": "percent",
        "claimed_value": -16,
        "claim_id": "claim_003",
        "comparison_period": "Q3 2025",
        "speaker_role": "cfo",
        "confidence": 1,
        "quote_text": "Automotive gross profit was flat sequentially despite 16% lower deliveries, primarily due to regional mix",
        "gaap_classification": "gaap",
        "quote_end_char": 8759,
        "claim_type": "qoq_growth",
        "speaker": "Vaibhav Taneja",
        "is_approximate": false,
        "claimed_value_raw": "16% lower",
        "metric_context": "Total",
        "metric_type": "other",
        "scale": null,
        "quote_start_char": 8654,
        "period": "Q4 2025"
      },
      "verification": {
        "claim_id": "claim_003",
        "claimed_value": -16,
        "actual_value": null,
        "difference": null,
        "difference_pct": null,
        "tolerance_used": null,
        "computation_detail": null,
        "computation_steps": [],
        "financial_facts_used": [],
        "evidence_source": null,
        "flags": [],
        "misleading_flags": [],
        "misleading_reasons": [],
        "explanation": "Metric 'other' not in verification catalog.",
        "verdict": "unverifiable"
      }
    },
    {
      "claim": {
        "metric_type": "other",
        "metric_context": "FSD",
        "scale": null,
        "quote_start_char": 9200,
        "period": "Q4 2025",
        "gaap_classification": "gaap",
        "claim_type": "absolute",
        "quote_end_char": 9300,
        "is_approximate": true,
        "speaker": "Vaibhav Taneja",
        "claimed_value_raw": "1,100,000",
        "speaker_role": "cfo",
        "confidence": 1,
        "quote_text": "FSD adoption continued to improve in the quarter, reaching nearly 1,100,000 paid customers globally.",
        "claimed_value": 1100000,
        "claim_id": "claim_004",
        "unit": "count",
        "qualifiers": [
          "nearly"
        ]
      },
      "verification": {
        "claim_id": "claim_004",
        "claimed_value": 1100000,
        "actual_value": null,
        "difference": null,
        "difference_pct": null,
        "tolerance_used": null,
        "computation_detail": null,
        "computation_steps": [],
        "financial_facts_used": [],
        "evidence_source": null,
        "flags": [],
        "misleading_flags": [],
        "misleading_reasons": [],
        "explanation": "Metric 'other' not in verification catalog.",
        "verdict": "unverifiable"
      }
    },
    {
      "claim": {
        "confidence": 1,
        "speaker_role": "cfo",
        "quote_text": "Of these, nearly 70% were upfront purchases.",
        "unit": "percent",
        "claimed_value": 70,
        "claim_id": "claim_005",
        "qualifiers": [
          "nearly"
        ],
        "scale": null,
        "quote_start_char": 9301,
        "metric_context": "FSD",
        "metric_type": "other",
        "period": "Q4 2025",
        "quote_end_char": 9345,
        "claim_type": "absolute",
        "gaap_classification": "gaap",
        "claimed_value_raw": "70%",
        "speaker": "Vaibhav Taneja",
        "is_approximate": true
      },
      "verification": {
        "claim_id": "claim_005",
        "claimed_value": 70,
        "actual_value": null,
        "difference": null,
        "difference_pct": null,
        "tolerance_used": null,
        "computation_detail": null,
        "computation_steps": [],
        "financial_facts_used": [],
        "evidence_source": null,
        "flags": [],
        "misleading_flags": [],
        "misleading_reasons": [],
        "explanation": "Metric 'other' not in verification catalog.",
        "verdict": "unverifiable"
      }
    },
    {
      "claim": {
        "quote_text": "On the energy front, we achieved yet another record in terms of gross profit for the quarter and ended the year with nearly $12.8 billion in revenue, a 26.6% year-over-year growth.",
        "speaker_role": "cfo",
        "confidence": 1,
        "qualifiers": [
          "nearly"
        ],
        "claimed_value": 12.8,
        "claim_id": "claim_006",
        "unit": "dollars",
        "period": "FY 2025",
        "metric_type": "revenue",
        "metric_context": "Energy",
        "scale": "billions",
        "quote_start_char": 9602,
        "is_approximate": true,
        "speaker": "Vaibhav Taneja",
        "claimed_value_raw": "$12.8 billion",
        "gaap_classification": "gaap",
        "claim_type": "absolute",
        "quote_end_char": 9782
      },
      "verification": {
        "claim_id": "claim_006",
        "claimed_value": 12.8,
        "actual_value": null,
        "difference": null,
        "difference_pct": null,
        "tolerance_used": null,
        "computation_detail": null,
        "computation_steps": [],
        "financial_facts_used": [],
        "evidence_source": null,
        "flags": [
          "segment_claim"
        ],
        "misleading_flags": [],
        "misleading_reasons": [],
        "explanation": "This is a Energy revenue claim. Our data only includes total company-level figures.",
        "verdict": "unverifiable"
      }
    },
    {
      "claim": {
        "speaker": "Vaibhav Taneja",
        "is_approximate": false,
        "claimed_value_raw": "10.5%",
        "gaap_classification": "gaap",
        "quote_end_char": 10328,
        "claim_type": "absolute",
        "period": "Q3 2025",
        "metric_context": "Services and others",
        "metric_type": "gross_margin",
        "scale": null,
        "quote_start_char": 10209,
        "unit": "percent",
        "claimed_value": 10.5,
        "claim_id": "claim_008",
        "quote_text": "Services and others margin declined from 10.5% to 8.8% primarily from higher employee-related costs for service centers",
        "speaker_role": "cfo",
        "confidence": 1
      },
      "verification": {
        "claim_id": "claim_008",
        "claimed_value": 10.5,
        "actual_value": null,
        "difference": null,
        "difference_pct": null,
        "tolerance_used": null,
        "computation_detail": null,
        "computation_steps": [],
        "financial_facts_used": [],
        "evidence_source": null,
        "flags": [],
        "misleading_flags": [],
        "misleading_reasons": [],
        "explanation": "No gross_margin data found for TSLA Q3 2025.",
        "verdict": "unverifiable"
      }
    },
    {
      "claim": {
        "claimed_value": 20.1,
        "claim_id": "claim_010",
        "unit": "percent",
        "qualifiers": [
          "over"
        ],
        "speaker_role": "cfo",
        "confidence": 1,
        "quote_text": "On total gross margin front, we ended the quarter with over 20.1%, something which we haven't achieved for over the last two years.",
        "gaap_classification": "gaap",
        "claim_type": "absolute",
        "quote_end_char": 10965,
        "is_approximate": false,
        "speaker": "Vaibhav Taneja",
        "claimed_value_raw": "20.1%",
        "metric_type": "gross_margin",
        "metric_context": "Total",
        "scale": null,
        "quote_start_char": 10834,
        "period": "Q4 2025"
      },
      "verification": {
        "claim_id": "claim_010",
        "claimed_value": 20.1,
        "actual_value": null,
        "difference": null,
        "difference_pct": null,
        "tolerance_used": null,
        "computation_detail": null,
        "computation_steps": [],
        "financial_facts_used": [],
        "evidence_source": null,
        "flags": [],
        "misleading_flags": [],
        "misleading_reasons": [],
        "explanation": "No gross_margin data found for TSLA Q4 2025.",
        "verdict": "unverifiable"
      }
    },
    {
      "claim": {
        "speaker_role": "cfo",
        "confidence": 1,
        "quote_text": "operating expenses increased sequentially $500 million in Q4, primarily from increased stock-based compensation for employees",
        "claimed_value": 500,
        "claim_id": "claim_011",
        "unit": "dollars",
        "comparison_period": "Q3 2025",
        "metric_type": "operating_expenses",
        "metric_context": "Total",
        "scale": "millions",
        "quote_start_char": 11089,
        "period": "Q4 2025",
        "gaap_classification": "gaap",
        "claim_type": "qoq_growth",
        "quote_end_char": 11214,
        "is_approximate": false,
        "speaker": "Vaibhav Taneja",
        "claimed_value_raw": "$500 million"
      },
      "verification": {
        "claim_id": "claim_011",
        "claimed_value": 500,
        "actual_value": null,
        "difference": null,
        "difference_pct": null,
        "tolerance_used": null,
        "computation_detail": null,
        "computation_steps": [],
        "financial_facts_used": [],
        "evidence_source": null,
        "flags": [
          "dollar_amount_growth"
        ],
        "misleading_flags": [],
        "misleading_reasons": [],
        "explanation": "This growth claim appears to use a dollar amount rather than a percentage. Dollar-amount changes cannot be compared against percentage growth computations.",
        "verdict": "unverifiable"
      }
    },
    {
      "claim": {
        "quote_text": "Net income was negatively impacted from mark-to-market charges on a Bitcoin holding, which depreciated 23% as compared to the last quarter",
        "confidence": 1,
        "speaker_role": "cfo",
        "claim_id": "claim_012",
        "claimed_value": 23,
        "unit": "percent",
        "period": "Q4 2025",
        "quote_start_char": 11586,
        "scale": null,
        "metric_type": "other",
        "metric_context": "Total",
        "claimed_value_raw": "23%",
        "is_approximate": false,
        "speaker": "Vaibhav Taneja",
        "claim_type": "absolute",
        "quote_end_char": 11724,
        "gaap_classification": "gaap"
      },
      "verification": {
        "claim_id": "claim_012",
        "claimed_value": 23,
        "actual_value": null,
        "difference": null,
        "difference_pct": null,
        "tolerance_used": null,
        "computation_detail": null,
        "computation_steps": [],
        "financial_facts_used": [],
        "evidence_source": null,
        "flags": [],
        "misleading_flags": [],
        "misleading_reasons": [],
        "explanation": "Metric 'other' not in verification catalog.",
        "verdict": "unverifiable"
      }
    },
    {
      "claim": {
        "claimed_value_raw": "$1.4 billion",
        "speaker": "Vaibhav Taneja",
        "is_approximate": false,
        "quote_end_char": 11877,
        "claim_type": "absolute",
        "gaap_classification": "unknown",
        "period": "Q4 2025",
        "scale": "billions",
        "quote_start_char": 11820,
        "metric_context": "Total",
        "metric_type": "free_cash_flow",
        "unit": "dollars",
        "claimed_value": 1.4,
        "claim_id": "claim_013",
        "quote_text": "On the free cash flow front, we ended up at $1.4 billion.",
        "confidence": 1,
        "speaker_role": "cfo"
      },
      "verification": {
        "claim_id": "claim_013",
        "claimed_value": 1.4,
        "actual_value": 1420000000,
        "difference": -20000000.0,
        "difference_pct": 1.4084507042253522,
        "tolerance_used": 0.02,
        "computation_detail": "Claimed 1,400,000,000.00 vs Actual 1,420,000,000.00. Diff: 1.41% (threshold: 2.0%)",
        "computation_steps": [
          {
            "step": "Absolute comparison",
            "formula": "|1,400,000,000.00 - 1,420,000,000.00| / |1,420,000,000.00|",
            "result": 0.014084507042253521,
            "threshold": 0.02
          }
        ],
        "financial_facts_used": [
          {
            "field": "free_cash_flow",
            "fy": 2025,
            "fq": 4,
            "value": 1420000000
          }
        ],
        "evidence_source": "fmp",
        "flags": [],
        "misleading_flags": [],
        "misleading_reasons": [],
        "explanation": "Verified: claimed 1,400,000,000.00 vs actual 1,420,000,000.00 from fmp.",
        "verdict": "verified"
      }
    },
    {
      "claim": {
        "confidence": 1,
        "speaker_role": "cfo",
        "quote_text": "We did end up CapEx being slightly below our previous guidance of $9 billion.",
        "claimed_value": 9,
        "claim_id": "claim_014",
        "unit": "dollars",
        "qualifiers": [
          "slightly below"
        ],
        "scale": "billions",
        "quote_start_char": 11878,
        "metric_type": "capital_expenditures",
        "metric_context": "Total",
        "period": "FY 2025",
        "claim_type": "absolute",
        "quote_end_char": 11955,
        "gaap_classification": "gaap",
        "claimed_value_raw": "$9 billion",
        "is_approximate": true,
        "speaker": "Vaibhav Taneja"
      },
      "verification": {
        "claim_id": "claim_014",
        "claimed_value": 9,
        "actual_value": 8527000000.0,
        "difference": null,
        "difference_pct": null,
        "tolerance_used": null,
        "computation_detail": null,
        "computation_steps": [],
        "financial_facts_used": [
          {
            "field": "capital_expenditures",
            "fy": 2025,
            "fq": 1,
            "value": 1492000000
          },
          {
            "field": "capital_expenditures",
            "fy": 2025,
            "fq": 2,
            "value": 2394000000
          },
          {
            "field": "capital_expenditures",
            "fy": 2025,
            "fq": 3,
            "value": 2248000000
          },
          {
            "field": "capital_expenditures",
            "fy": 2025,
            "fq": 4,
            "value": 2393000000
          }
        ],
        "evidence_source": "fmp",
        "flags": [
          "capex_definition_gap"
        ],
        "misleading_flags": [],
        "misleading_reasons": [],
        "explanation": "Claimed CapEx ($9.0B) exceeds reported cash CapEx ($8.5B) by 6%. Companies often report CapEx including finance leases on calls, while data sources report cash CapEx only.",
        "verdict": "unverifiable"
      }
    },
    {
      "claim": {
        "quote_text": "At the moment, we are expecting that CapEx would be in excess of $20 billion.",
        "speaker_role": "cfo",
        "confidence": 1,
        "qualifiers": [
          "in excess of"
        ],
        "unit": "dollars",
        "claimed_value": 20,
        "claim_id": "claim_015",
        "period": "FY 2026",
        "metric_context": "Total",
        "metric_type": "capital_expenditures",
        "quote_start_char": 12068,
        "scale": "billions",
        "speaker": "Vaibhav Taneja",
        "is_approximate": true,
        "claimed_value_raw": "$20 billion",
        "gaap_classification": "gaap",
        "quote_end_char": 12145,
        "claim_type": "guidance"
      },
      "verification": {
        "claim_id": "claim_015",
        "claimed_value": 20,
        "actual_value": null,
        "difference": null,
        "difference_pct": null,
        "tolerance_used": null,
        "computation_detail": null,
        "computation_steps": [],
        "financial_facts_used": [],
        "evidence_source": null,
        "flags": [
          "guidance_claim"
        ],
        "misleading_flags": [],
        "misleading_reasons": [],
        "explanation": "Forward-looking guidance claims cannot be verified against historical data.",
        "verdict": "unverifiable"
      }
    },
    {
      "claim": {
        "quote_end_char": 34640,
        "claim_type": "absolute",
        "gaap_classification": "gaap",
        "claimed_value_raw": "$44 billion",
        "speaker": "Vaibhav Taneja",
        "is_approximate": false,
        "scale": "billions",
        "quote_start_char": 34556,
        "metric_context": "Total",
        "metric_type": "other",
        "period": "Q4 2025s",
        "unit": "dollars",
        "claimed_value": 44,
        "claim_id": "claim_016",
        "qualifiers": [
          "over"
        ],
        "confidence": 1,
        "speaker_role": "cfo",
        "quote_text": "Initially, obviously, we have over $44 billion of cash and investments on the books."
      },
      "verification": {
        "claim_id": "claim_016",
        "claimed_value": 44,
        "actual_value": null,
        "difference": null,
        "difference_pct": null,
        "tolerance_used": null,
        "computation_detail": null,
        "computation_steps": [],
        "financial_facts_used": [],
        "evidence_source": null,
        "flags": [],
        "misleading_flags": [],
        "misleading_reasons": [],
        "explanation": "No cash_and_marketable_securities data found for TSLA Q4 2025.",
        "verdict": "unverifiable"
      }
    }
  ],
  "summary": {
    "total": 13,
    "verified": 1,
    "close_match": 0,
    "mismatch": 0,
    "misleading": 0,
    "unverifiable": 12
  }
}